Electrum_Zcash_Random_Fork-3.1.3b5.data/scripts/electrum-zcash
Electrum_Zcash_Random_Fork-3.1.3b5.dist-info/DESCRIPTION.rst
Electrum_Zcash_Random_Fork-3.1.3b5.dist-info/METADATA
Electrum_Zcash_Random_Fork-3.1.3b5.dist-info/RECORD
Electrum_Zcash_Random_Fork-3.1.3b5.dist-info/WHEEL
Electrum_Zcash_Random_Fork-3.1.3b5.dist-info/metadata.json
Electrum_Zcash_Random_Fork-3.1.3b5.dist-info/top_level.txt
electrum_zcash/__init__.py
electrum_zcash/base_wizard.py
electrum_zcash/bitcoin.py
electrum_zcash/blockchain.py
electrum_zcash/coinchooser.py
electrum_zcash/commands.py
electrum_zcash/constants.py
electrum_zcash/contacts.py
electrum_zcash/daemon.py
electrum_zcash/dnssec.py
electrum_zcash/exchange_rate.py
electrum_zcash/i18n.py
electrum_zcash/interface.py
electrum_zcash/jsonrpc.py
electrum_zcash/keystore.py
electrum_zcash/mnemonic.py
electrum_zcash/msqr.py
electrum_zcash/network.py
electrum_zcash/old_mnemonic.py
electrum_zcash/paymentrequest.py
electrum_zcash/paymentrequest_pb2.py
electrum_zcash/pem.py
electrum_zcash/plot.py
electrum_zcash/plugins.py
electrum_zcash/qrscanner.py
electrum_zcash/ripemd.py
electrum_zcash/rsakey.py
electrum_zcash/simple_config.py
electrum_zcash/storage.py
electrum_zcash/synchronizer.py
electrum_zcash/transaction.py
electrum_zcash/util.py
electrum_zcash/verifier.py
electrum_zcash/version.py
electrum_zcash/wallet.py
electrum_zcash/websockets.py
electrum_zcash/x509.py
electrum_zcash_gui/__init__.py
electrum_zcash_gui/stdio.py
electrum_zcash_gui/text.py
electrum_zcash_gui/qt/__init__.py
electrum_zcash_gui/qt/address_dialog.py
electrum_zcash_gui/qt/address_list.py
electrum_zcash_gui/qt/amountedit.py
electrum_zcash_gui/qt/completion_text_edit.py
electrum_zcash_gui/qt/console.py
electrum_zcash_gui/qt/contact_list.py
electrum_zcash_gui/qt/exception_window.py
electrum_zcash_gui/qt/fee_slider.py
electrum_zcash_gui/qt/history_list.py
electrum_zcash_gui/qt/installwizard.py
electrum_zcash_gui/qt/invoice_list.py
electrum_zcash_gui/qt/main_window.py
electrum_zcash_gui/qt/network_dialog.py
electrum_zcash_gui/qt/password_dialog.py
electrum_zcash_gui/qt/paytoedit.py
electrum_zcash_gui/qt/qrcodewidget.py
electrum_zcash_gui/qt/qrtextedit.py
electrum_zcash_gui/qt/qrwindow.py
electrum_zcash_gui/qt/request_list.py
